README.md
setup.py
common/__init__.py
common/common_utils.py
common/global_constants.py
common/singleton.py
device/__init__.py
device/base_device.py
device/device_class_def.py
device/device_config.py
device/device_config_manager.py
device/port/__init__.py
device/port/bt_port.py
device/port/com_port.py
device/port/eth_port.py
device/port/lpt_port.py
device/port/mock_port.py
device/port/port.py
device/port/shared_device_port.py
device/port/usb_port.py
device/status/__init__.py
device/status/device_status.py
device/status/device_status_receiver.py
driver/__init__.py
driver/driver_plugin.py
driver/evaluator.py
driver/file_printer.py
driver/finance_ic_card_rwer.py
driver/finger_scanner.py
driver/id_card_reader.py
driver/keypad.py
driver/magnetic_strip_rwer.py
driver/multi_func_keypad.py
driver/multi_func_screen.py
driver/shared_device_client.py
driverApi.egg-info/PKG-INFO
driverApi.egg-info/SOURCES.txt
driverApi.egg-info/dependency_links.txt
driverApi.egg-info/top_level.txt
logger/__init__.py
logger/device_logger.py