Metadata-Version: 2.1
Name: driverApi
Version: 1.0.7
Summary: 外设驱动接口
Author: NanYuan
Author-email: 28766392428@qq.com
Classifier: Programming Language :: Python :: 3.10
Classifier: Operating System :: OS Independent
